__init__.py
llm_jina/__init__.py
llm_jina/api.py
llm_jina/api_updated.py
llm_jina/commands.py
llm_jina/exceptions.py
llm_jina/metaprompt.py
llm_jina/utils.py
llm_jina/code_agent/__init__.py
llm_jina/code_agent/executor.py
llm_jina/code_agent/generator.py
llm_jina/code_agent/refiner.py
llm_jina/code_agent/utils.py
llm_jina/code_agent/validator.py
llm_jina-0.3.0.dist-info/METADATA
llm_jina-0.3.0.dist-info/WHEEL
llm_jina-0.3.0.dist-info/entry_points.txt
llm_jina-0.3.0.dist-info/top_level.txt
llm_jina-0.3.0.dist-info/RECORD
